rich_sparklines/__init__.py
rich_sparklines-0.1.5.dist-info/WHEEL
rich_sparklines-0.1.5.dist-info/METADATA
rich_sparklines-0.1.5.dist-info/RECORD
