Metadata-Version: 2.1
Name: rich-sparklines
Version: 0.1.5
Summary: Integrate rich and sparklines libraries
License: MIT
Author: Elliana
Author-email: me@mause.me
Requires-Python: >=3.8,<4.0
Classifier: License :: OSI Approved :: MIT License
Classifier: Programming Language :: Python :: 3
Classifier: Programming Language :: Python :: 3.8
Requires-Dist: rich (>=7.1.0,<8.0.0)
Requires-Dist: sparklines (>=0.4.2,<0.5.0)
